{
  "spam.call": {
    "title": "Спам",
    "description": "Нежелательные рекламные звонки, навязчивые предложения и автоматические обзвоны.",
    "examples": [
      "это рекламный звонок",
      "навязывают услугу без запроса",
      "это спам",
      "не интересует, удалите номер"
    ],
    "default_group": "support",
    "priority": "high"
  },
  "consulting": {
    "title": "Консультация",
    "description": "Клиенту нужна консультация по возможностям продукта или услуги.",
    "examples": [
      "нужна консультация",
      "расскажите подробнее про ваши услуги",
      "хочу получить консультацию специалиста",
      "подскажите, какой вариант мне подойдет"
    ],
    "default_group": "consulting",
    "priority": "medium"
  },
  "cooperation": {
    "title": "Сотрудничество",
    "description": "Партнерство, конференции, деловые предложения и внешние инициативы по сотрудничеству.",
    "examples": [
      "хотим пригласить вашу компанию на конференцию",
      "приглашаем вас выступить на мероприятии",
      "интересует участие в вашем мероприятии",
      "рассматриваем вас как партнера"
    ],
    "default_group": "cooperation_department",
    "priority": "medium"
  },
  "courses": {
    "title": "Обучение",
    "description": "Запросы про курсы, программы обучения, расписание и стоимость.",
    "examples": [
      "хочу записаться на курс",
      "какие есть программы обучения",
      "интересует обучение сотрудников",
      "подскажите стоимость курса"
    ],
    "default_group": "education_center",
    "priority": "medium"
  },
  "license": {
    "title": "Продажа / лицензия",
    "description": "Запросы на покупку, подключение, оформление услуги или лицензии.",
    "examples": [
      "хочу купить вашу услугу",
      "как оформить подключение",
      "готов заключить договор",
      "нужно оформить заказ"
    ],
    "default_group": "sales",
    "priority": "high"
  },
  "portal_access": {
    "title": "Доступ в портал",
    "description": "Проблемы с доступом, авторизацией и работой в личном кабинете или портале.",
    "examples": [
      "не могу войти в личный кабинет",
      "не приходит код подтверждения",
      "ошибка авторизации в портале",
      "нужен доступ в систему"
    ],
    "default_group": "support",
    "priority": "high"
  },
  "misc.triage": {
    "title": "Неопределенное обращение",
    "description": "Не хватает контекста для уверенной маршрутизации в профильный отдел.",
    "examples": [
      "алло",
      "есть вопрос",
      "подскажите пожалуйста",
      "не знаю к кому обратиться"
    ],
    "default_group": "support",
    "priority": "medium"
  }
}
